drop_duplicates_nested_list/LICENSE
drop_duplicates_nested_list/README.MD
drop_duplicates_nested_list/__init__.py
drop_duplicates_nested_list/requirements.txt
drop_duplicates_nested_list/thirdparty.json
drop_duplicates_nested_list-0.10.dist-info/LICENSE.rst
drop_duplicates_nested_list-0.10.dist-info/METADATA
drop_duplicates_nested_list-0.10.dist-info/WHEEL
drop_duplicates_nested_list-0.10.dist-info/top_level.txt
drop_duplicates_nested_list-0.10.dist-info/RECORD
